markdown_to_testcase/__init__.py
markdown_to_testcase/__main__.py
markdown_to_testcase/cli.py
markdown_to_testcase/converter.py
markdown_to_testcase/main.py
markdown_to_testcase/parser.py
markdown_to_testcase-0.1.0a1.dist-info/LICENSE
markdown_to_testcase-0.1.0a1.dist-info/METADATA
markdown_to_testcase-0.1.0a1.dist-info/WHEEL
markdown_to_testcase-0.1.0a1.dist-info/entry_points.txt
markdown_to_testcase-0.1.0a1.dist-info/top_level.txt
markdown_to_testcase-0.1.0a1.dist-info/RECORD
