Metadata-Version: 2.2
Name: markdown_to_testcase
Version: 0.1.0a1
Summary: A tool to extract test cases from markdown files and convert them to CSV and Excel
Author-email: Taka Suzuki <tkykszk@example.com>
License: MIT
Project-URL: Homepage, https://github.com/tkykszk/markdown_to_testcase
Project-URL: Bug Tracker, https://github.com/tkykszk/markdown_to_testcase/issues
Project-URL: Documentation, https://markdown-to-testcase.readthedocs.io/
Classifier: Programming Language :: Python :: 3
Classifier: Programming Language :: Python :: 3.12
Classifier: License :: OSI Approved :: MIT License
Classifier: Operating System :: OS Independent
Classifier: Topic :: Software Development :: Testing
Classifier: Topic :: Text Processing :: Markup :: Markdown
Requires-Python: >=3.12
License-File: LICENSE
Requires-Dist: loguru>=0.7.2
Requires-Dist: openpyxl>=3.1.2
Requires-Dist: markdown-it-py>=3.0.0
Requires-Dist: pyyaml>=6.0.1
Requires-Dist: typer>=0.9.0
Requires-Dist: yamllint>=1.33.0
